progress/__init__.py
progress/progress.py
mortalprogressbar-1.0.1.dist-info/METADATA
mortalprogressbar-1.0.1.dist-info/WHEEL
mortalprogressbar-1.0.1.dist-info/top_level.txt
mortalprogressbar-1.0.1.dist-info/RECORD
