Metadata-Version: 2.1
Name: mortalprogressbar
Version: 1.0.1
Summary: A package for simple progress bar
Home-page: https://github.com/zxcj04/Progress-bar
Author: FanRende Huang
